chalicelib_fourfront/__init__.py
chalicelib_fourfront/app_utils.py
chalicelib_fourfront/check_schedules.py
chalicelib_fourfront/check_setup.json
chalicelib_fourfront/checks/__init__.py
chalicelib_fourfront/checks/audit_checks.py
chalicelib_fourfront/checks/badge_checks.py
chalicelib_fourfront/checks/check_utils.py
chalicelib_fourfront/checks/deployment_checks.py
chalicelib_fourfront/checks/ecs_checks.py
chalicelib_fourfront/checks/es_checks.py
chalicelib_fourfront/checks/header_checks.py
chalicelib_fourfront/checks/helpers/confchecks.py
chalicelib_fourfront/checks/helpers/es_utils.py
chalicelib_fourfront/checks/helpers/google_utils.py
chalicelib_fourfront/checks/helpers/wfr_utils.py
chalicelib_fourfront/checks/helpers/wfrset_utils.py
chalicelib_fourfront/checks/helpers/wrangler_utils.py
chalicelib_fourfront/checks/higlass_checks.py
chalicelib_fourfront/checks/release_updates_checks.py
chalicelib_fourfront/checks/system_checks.py
chalicelib_fourfront/checks/wfr_checks.py
chalicelib_fourfront/checks/wfr_encode_checks.py
chalicelib_fourfront/checks/wrangler_checks.py
chalicelib_fourfront/gitinfo.json
chalicelib_fourfront/package.py
chalicelib_fourfront/scripts/local_check_execution.py
chalicelib_fourfront/vars.py
foursight-4.9.29.dist-info/LICENSE.txt
foursight-4.9.29.dist-info/METADATA
foursight-4.9.29.dist-info/WHEEL
foursight-4.9.29.dist-info/entry_points.txt
foursight-4.9.29.dist-info/RECORD
